{
  "/authentication": [
    {
      "id": "using-your-api-key",
      "title": "Using your API Key",
      "offsetRem": 0
    },
    {
      "id": "errors",
      "title": "Errors",
      "offsetRem": 0
    }
  ],
  "/docs": [
    {
      "id": "features",
      "title": "Features",
      "offsetRem": 0
    },
    {
      "id": "next-steps",
      "title": "Next Steps",
      "offsetRem": 0
    }
  ],
  "/health": [
    {
      "id": "get-status",
      "title": "Get Status",
      "offsetRem": 0
    },
    {
      "id": "attributes",
      "title": "Attributes",
      "offsetRem": 0
    }
  ],
  "/errors": [
    {
      "id": "status-codes",
      "title": "Status Codes",
      "offsetRem": 0
    },
    {
      "id": "error-response-format",
      "title": "Error Response Format",
      "offsetRem": 0
    }
  ],
  "/universal": [
    {
      "id": "the-correction-model",
      "title": "The Correction Model",
      "offsetRem": 0
    },
    {
      "id": "attributes",
      "title": "Attributes",
      "offsetRem": 0
    }
  ],
  "/validate": [
    {
      "id": "check-subtitles",
      "title": "Check Subtitles",
      "offsetRem": 0
    },
    {
      "id": "attributes",
      "title": "Attributes",
      "offsetRem": 0
    }
  ]
}